{
  "id": 430,
  "mission": "000000000000000000000000000000000000000000000000000000000000000000000000000000000",
  "solution": "247913568195687342863254197312479685958162734674538219526891473439726851781345926",
  "win_rate": 64.5,
  "cages": [
    [
      9,
      18,
      27
    ],
    [
      54,
      63
    ],
    [
      0,
      1
    ],
    [
      10,
      11,
      19,
      20
    ],
    [
      28,
      37
    ],
    [
      36,
      45,
      46,
      55
    ],
    [
      72,
      73
    ],
    [
      2
    ],
    [
      29,
      38,
      39
    ],
    [
      47,
      48
    ],
    [
      64,
      65
    ],
    [
      21,
      22,
      30
    ],
    [
      56,
      57
    ],
    [
      66,
      74,
      75,
      76
    ],
    [
      4,
      5
    ],
    [
      3,
      12,
      13
    ],
    [
      40,
      49
    ],
    [
      58,
      59
    ],
    [
      31,
      32,
      41,
      50
    ],
    [
      14,
      15,
      23,
      24
    ],
    [
      42,
      51
    ],
    [
      60,
      61
    ],
    [
      67,
      68,
      69
    ],
    [
      77,
      78
    ],
    [
      6,
      7
    ],
    [
      33,
      34
    ],
    [
      43,
      52
    ],
    [
      62,
      70,
      71
    ],
    [
      8,
      16,
      17,
      25
    ],
    [
      26,
      35
    ],
    [
      44,
      53
    ],
    [
      79,
      80
    ]
  ]
}