{
  "puzzleData": {
    "type": 2,
    "gridWidth": 9,
    "gridHeight": 9,
    "source": {
      "year": 2023,
      "month": 11,
      "day": 27,
      "variant": 10
    },
    "startingGrid": [
      5,
      0,
      3,
      0,
      2,
      0,
      0,
      0,
      8,
      0,
      3,
      0,
      0,
      0,
      1,
      0,
      2,
      0,
      0,
      6,
      1,
      4,
      5,
      0,
      0,
      0,
      9,
      0,
      1,
      0,
      0,
      9,
      0,
      0,
      0,
      0,
      0,
      0,
      7,
      0,
      3,
      0,
      8,
      0,
      1,
      0,
      0,
      0,
      0,
      4,
      3,
      0,
      7,
      0,
      3,
      0,
      0,
      0,
      0,
      2,
      7,
      6,
      0,
      6,
      0,
      0,
      5,
      0,
      0,
      0,
      0,
      0,
      0,
      0,
      5,
      0,
      6,
      4,
      0,
      0,
      0
    ],
    "layout": [
      2,
      2,
      2,
      2,
      2,
      8,
      7,
      7,
      7,
      2,
      1,
      2,
      2,
      6,
      8,
      8,
      7,
      7,
      2,
      1,
      6,
      6,
      6,
      6,
      8,
      7,
      7,
      1,
      1,
      6,
      6,
      4,
      4,
      8,
      5,
      7,
      1,
      1,
      1,
      6,
      4,
      8,
      8,
      5,
      7,
      0,
      1,
      0,
      6,
      4,
      8,
      8,
      5,
      5,
      0,
      1,
      0,
      0,
      4,
      4,
      4,
      4,
      5,
      0,
      0,
      0,
      0,
      4,
      3,
      3,
      3,
      5,
      3,
      3,
      3,
      3,
      3,
      3,
      5,
      5,
      5
    ],
    "extraRegions": []
  },
  "title": "Daily Easy Jigsaw Sudoku Puzzle for Monday 27th November 2023 (Easy)",
  "title1": "Daily Easy Jigsaw Sudoku Puzzle",
  "title2": "Monday 27th November 2023",
  "location": "/jigsawsudoku/easy/2023/11/27",
  "printlink": "/print/jigsawsudoku/easy/2023/11/27",
  "nextRandomPuzzleIndex": 5296,
  "nextPuzzleURL": "/jigsawsudoku/easy/2019/07/03"
}