{
  "id": 854,
  "mission": "000000050000050000000000008003009000000000600000000000000000002000003000060020000",
  "solution": "196284753832157496745396218613549827257831649984672531378415962429763185561928374",
  "win_rate": 64.39,
  "cages": [
    [
      0,
      9
    ],
    [
      18,
      19,
      27,
      28
    ],
    [
      36
    ],
    [
      45,
      54
    ],
    [
      63,
      64,
      72,
      73
    ],
    [
      1,
      10,
      11
    ],
    [
      37,
      46
    ],
    [
      2
    ],
    [
      20,
      29
    ],
    [
      55,
      56
    ],
    [
      65,
      74
    ],
    [
      21
    ],
    [
      30
    ],
    [
      38,
      39,
      47
    ],
    [
      48,
      57
    ],
    [
      66,
      75
    ],
    [
      4,
      5
    ],
    [
      3,
      12,
      13,
      14,
      22
    ],
    [
      40,
      49,
      58,
      59
    ],
    [
      67,
      68,
      69
    ],
    [
      76,
      77
    ],
    [
      31,
      32,
      41
    ],
    [
      6,
      7,
      8,
      15
    ],
    [
      23,
      24
    ],
    [
      50,
      51
    ],
    [
      78,
      79
    ],
    [
      16,
      17,
      25,
      26
    ],
    [
      33,
      42,
      43
    ],
    [
      52,
      60,
      61
    ],
    [
      70
    ],
    [
      34,
      35,
      44
    ],
    [
      53
    ],
    [
      62,
      71
    ],
    [
      80
    ]
  ]
}