{
  "id": 704,
  "mission": "000008000000000700300000000000000002000000400000400000060000003000010000000006000",
  "solution": "629178345158943726374652891437895162586231479912467538865724913243519687791386254",
  "win_rate": 56.93,
  "cages": [
    [
      0,
      9
    ],
    [
      45,
      54,
      63
    ],
    [
      1,
      2,
      3
    ],
    [
      10,
      18,
      19,
      20
    ],
    [
      28
    ],
    [
      27,
      36,
      37,
      46
    ],
    [
      48,
      55,
      56,
      57
    ],
    [
      72,
      73
    ],
    [
      29,
      38
    ],
    [
      47
    ],
    [
      64,
      65
    ],
    [
      74
    ],
    [
      11,
      12,
      21
    ],
    [
      30,
      39
    ],
    [
      66
    ],
    [
      49
    ],
    [
      58,
      59
    ],
    [
      67,
      75,
      76
    ],
    [
      4,
      5
    ],
    [
      14,
      15,
      23
    ],
    [
      13,
      22,
      31,
      40,
      41
    ],
    [
      68,
      69
    ],
    [
      6
    ],
    [
      24,
      25,
      26,
      34,
      35
    ],
    [
      32,
      33,
      42
    ],
    [
      50,
      51
    ],
    [
      43,
      52,
      60,
      61,
      70
    ],
    [
      77,
      78,
      79
    ],
    [
      7,
      16
    ],
    [
      8
    ],
    [
      17
    ],
    [
      44
    ],
    [
      53,
      62,
      71
    ],
    [
      80
    ]
  ]
}