{
  "id": 1062,
  "mission": "005000000000409000000000003300000000000000000000000007070000030800000900000000000",
  "solution": "415378269763429581928561473396745812157832694284196357672984135831257946549613728",
  "win_rate": 56.61,
  "cages": [
    [
      9
    ],
    [
      27,
      36,
      45,
      54
    ],
    [
      55,
      63,
      64,
      65
    ],
    [
      0,
      1,
      2,
      10
    ],
    [
      18,
      19
    ],
    [
      28,
      37,
      38
    ],
    [
      72,
      73
    ],
    [
      11,
      12,
      13
    ],
    [
      46,
      47
    ],
    [
      66,
      74,
      75
    ],
    [
      3
    ],
    [
      20,
      21,
      22
    ],
    [
      29,
      30,
      39,
      48
    ],
    [
      56,
      57
    ],
    [
      49,
      58
    ],
    [
      4,
      5,
      6,
      7
    ],
    [
      23
    ],
    [
      31,
      32,
      33,
      40,
      41
    ],
    [
      50,
      59
    ],
    [
      67,
      68
    ],
    [
      76,
      77
    ],
    [
      14,
      15,
      24
    ],
    [
      42
    ],
    [
      43,
      51,
      52
    ],
    [
      60,
      69,
      78
    ],
    [
      25,
      34
    ],
    [
      61,
      70,
      79
    ],
    [
      8
    ],
    [
      16,
      17,
      26,
      35
    ],
    [
      44,
      53
    ],
    [
      62,
      71
    ],
    [
      80
    ]
  ]
}